accera/Constants.py
accera/Debug.py
accera/Package.py
accera/Parameter.py
accera/Platforms.py
accera/Targets.py
accera/__init__.py
accera/_lang_python.cp38-win_amd64.pyd
accera/_version.py
accera/algorithms/NoneCacheHeuristics.py
accera/algorithms/__init__.py
accera/hat/__init__.py
accera/hat/onnx_hat_package.py
accera/lang/Array.py
accera/lang/Cache.py
accera/lang/DimensionUtilities.py
accera/lang/Function.py
accera/lang/IntrospectionUtilities.py
accera/lang/Layout.py
accera/lang/LogicFunction.py
accera/lang/LoopIndex.py
accera/lang/NativeLoopNestContext.py
accera/lang/Nest.py
accera/lang/Plan.py
accera/lang/Schedule.py
accera/lang/__init__.py
accera/samples/MatrixMultiplication.py
accera/samples/OfflineCacheMatrixMultiplication.py
accera/samples/__init__.py
accera/test/dsl_tests.py
accera/test/int_matmul_tests.py
accera/test/mfma_tests.py
accera/test/smoke_tests.py
accera/test/test_utils.py
accera/test/unit_tests.py
accera/test/verifiers.py
accera-1.2.29.dist-info/LICENSE
accera-1.2.29.dist-info/METADATA
accera-1.2.29.dist-info/WHEEL
accera-1.2.29.dist-info/top_level.txt
accera-1.2.29.dist-info/RECORD
