Metadata-Version: 2.1
Name: accera
Version: 1.2.29
Summary: Accera - An optimizing cross-compiler for compute-intensive code
Home-page: UNKNOWN
Author: Microsoft Research AI Compilers Team
Author-email: mlodev@microsoft.com
License: MIT License
Platform: Linux
Platform: Darwin
Platform: Windows
Classifier: License :: OSI Approved :: MIT License
Classifier: Intended Audience :: Developers
Classifier: Intended Audience :: Science/Research
Classifier: Topic :: Scientific/Engineering
Classifier: Topic :: Scientific/Engineering :: Mathematics
Classifier: Topic :: Scientific/Engineering :: Artificial Intelligence
Classifier: Topic :: Software Development
Classifier: Topic :: Software Development :: Libraries
Classifier: Topic :: Software Development :: Libraries :: Python Modules
Classifier: Programming Language :: C++
Classifier: Programming Language :: Python :: 3
Classifier: Programming Language :: Python :: 3.7
Classifier: Programming Language :: Python :: 3.8
Classifier: Programming Language :: Python :: 3.9
Classifier: Programming Language :: Python :: 3.10
Requires-Python: ~=3.7
Requires-Dist: termcolor
Requires-Dist: py-cpuinfo
Requires-Dist: varname
Requires-Dist: hatlib (==0.0.39)
Requires-Dist: numpy
Requires-Dist: pyyaml
Requires-Dist: tomlkit (<0.11.5,>=0.11.1)
Requires-Dist: accera-compilers
Requires-Dist: accera-gpu
Requires-Dist: accera-llvm (==15.0.101)
